MANIFEST.in
README.rst
setup.cfg
setup.py
data/eyedata.npy
pycasso/VERSION
pycasso/__init__.py
pycasso/core.py
pycasso/cutils.py
pycasso/libpath.py
pycasso.egg-info/PKG-INFO
pycasso.egg-info/SOURCES.txt
pycasso.egg-info/dependency_links.txt
pycasso.egg-info/not-zip-safe
pycasso.egg-info/requires.txt
pycasso.egg-info/top_level.txt
pycasso/lib/libpicasso.so
pycasso/src/Makefile
pycasso/src/amalgamation/picasso-all0.cpp
pycasso/src/build/c_api/c_api.d
pycasso/src/build/objective/gaussian_naive_update.d
pycasso/src/build/objective/glm.d
pycasso/src/build/objective/sqrtmse.d
pycasso/src/build/solver/actgd.d
pycasso/src/build/solver/actnewton.d
pycasso/src/build/solver/cli_main.d
pycasso/src/build/solver/solver_params.d
pycasso/src/include/eigen3/.git
pycasso/src/include/eigen3/.hgeol
pycasso/src/include/eigen3/.hgignore
pycasso/src/include/eigen3/.hgtags
pycasso/src/include/eigen3/CMakeLists.txt
pycasso/src/include/eigen3/COPYING.BSD
pycasso/src/include/eigen3/COPYING.GPL
pycasso/src/include/eigen3/COPYING.LGPL
pycasso/src/include/eigen3/COPYING.MINPACK
pycasso/src/include/eigen3/COPYING.MPL2
pycasso/src/include/eigen3/COPYING.README
pycasso/src/include/eigen3/CTestConfig.cmake
pycasso/src/include/eigen3/CTestCustom.cmake.in
pycasso/src/include/eigen3/INSTALL
pycasso/src/include/eigen3/README.md
pycasso/src/include/eigen3/eigen3.pc.in
pycasso/src/include/eigen3/signature_of_eigen3_matrix_library
pycasso/src/include/eigen3/Eigen/CMakeLists.txt
pycasso/src/include/eigen3/Eigen/Cholesky
pycasso/src/include/eigen3/Eigen/CholmodSupport
pycasso/src/include/eigen3/Eigen/Core
pycasso/src/include/eigen3/Eigen/Dense
pycasso/src/include/eigen3/Eigen/Eigen
pycasso/src/include/eigen3/Eigen/Eigenvalues
pycasso/src/include/eigen3/Eigen/Geometry
pycasso/src/include/eigen3/Eigen/Householder
pycasso/src/include/eigen3/Eigen/IterativeLinearSolvers
pycasso/src/include/eigen3/Eigen/Jacobi
pycasso/src/include/eigen3/Eigen/KLUSupport
pycasso/src/include/eigen3/Eigen/LU
pycasso/src/include/eigen3/Eigen/MetisSupport
pycasso/src/include/eigen3/Eigen/OrderingMethods
pycasso/src/include/eigen3/Eigen/PaStiXSupport
pycasso/src/include/eigen3/Eigen/PardisoSupport
