Metadata-Version: 1.2
Name: pycasso
Version: 0.1.2.2
Summary: Picasso Python Package
Home-page: https://hmjianggatech.github.io/picasso/
Maintainer: Haoming Jiang
Maintainer-email: jianghm.ustc@gmail.com
License: GPL-3.0
Platform: UNKNOWN
Classifier: Development Status :: 3 - Alpha
Classifier: Intended Audience :: Developers
Classifier: Intended Audience :: Science/Research
Classifier: Topic :: Scientific/Engineering :: Artificial Intelligence
Classifier: Topic :: Scientific/Engineering :: Mathematics
Classifier: Programming Language :: Python :: 3 :: Only
Classifier: License :: OSI Approved :: GNU General Public License v3 (GPLv3)
